trainloop/__init__.py
trainloop/trainloop.py
trainloop_sdk-0.1.11.dist-info/METADATA
trainloop_sdk-0.1.11.dist-info/WHEEL
trainloop_sdk-0.1.11.dist-info/top_level.txt
trainloop_sdk-0.1.11.dist-info/RECORD
